README.rst
setup.py
odoo_gateway/__init__.py
odoo_gateway/broadcast.py
odoo_gateway/decorators.py
odoo_gateway/faults.py
odoo_gateway/session.py
odoo_gateway/test.py
odoo_gateway/utils.py
odoo_gateway.egg-info/PKG-INFO
odoo_gateway.egg-info/SOURCES.txt
odoo_gateway.egg-info/dependency_links.txt
odoo_gateway.egg-info/entry_points.txt
odoo_gateway.egg-info/top_level.txt