Metadata-Version: 1.0
Name: odoo-gateway
Version: 0.131
Summary: Simple and powerfull tools for programming in Odoo framework (f.e shell, reference to models in stand-alone applications, Mediator pattern for intermodel communications)
Home-page: https://bitbucket.org/panaetov/odoo_gateway/overview
Author: Panaetov Alexey
Author-email: panaetovaa@gmail.com
License: BSD
Keywords: odoo openerp shell models stand-alone
Platform: UNKNOWN
